{
  "name": "Словарь",
  "abc": [
    {
      "key": "a",
      "value": "эй "
    },
    {
      "key": "b",
      "value": "би "
    },
    {
      "key": "c",
      "value": "си "
    },
    {
      "key": "d",
      "value": "ди "
    },
    {
      "key": "e",
      "value": "и "
    },
    {
      "key": "f",
      "value": "эф "
    },
    {
      "key": "g",
      "value": "джи "
    },
    {
      "key": "h",
      "value": "эйч "
    },
    {
      "key": "i",
      "value": "ай "
    },
    {
      "key": "j",
      "value": "джей "
    },
    {
      "key": "k",
      "value": "кей "
    },
    {
      "key": "l",
      "value": "эл "
    },
    {
      "key": "m",
      "value": "эм "
    },
    {
      "key": "n",
      "value": "эн "
    },
    {
      "key": "o",
      "value": "оу "
    },
    {
      "key": "p",
      "value": "пи "
    },
    {
      "key": "q",
      "value": "кью "
    },
    {
      "key": "r",
      "value": "ар "
    },
    {
      "key": "s",
      "value": "эс "
    },
    {
      "key": "t",
      "value": "ти "
    },
    {
      "key": "u",
      "value": "ю "
    },
    {
      "key": "v",
      "value": "ви "
    },
    {
      "key": "w",
      "value": "дабл-ю "
    },
    {
      "key": "x",
      "value": "экс "
    },
    {
      "key": "y",
      "value": "уай "
    },
    {
      "key": "z",
      "value": "зед "
    },
    {
      "key": ".",
      "value": "точка "
    }
  ]
}